<Config>
   
	<append xpath="/lootcontainers">

		<lootgroup name="FuriousRamsayGroupStarterClothes1" count="all">
			<item name="apparelLongShirt" count="1"/>
			<item name="apparelDenimPants" count="1"/>
			<item name="apparelRunningShoesRegular" count="1"/>
		</lootgroup>

		<lootgroup name="FuriousRamsayGroupStarterClothes2" count="all">
			<item name="apparelTankTop" count="1"/>
			<item name="apparelSkirt" count="1"/>
		</lootgroup>

		<lootgroup name="FuriousRamsayGroupStarterClothes3" count="all">
			<item name="apparelTShirtPlain" count="1"/>
			<item name="apparelDenimPants" count="1"/>
			<item name="apparelRunningShoesRegular" count="1"/>
		</lootgroup>

		<lootgroup name="FuriousRamsayGroupStarterClothes4" count="all">
			<item name="apparelTShirtPlain" count="1"/>
			<item name="apparelDenimPants" count="1"/>
			<item name="apparelWornBoots" count="1"/>
		</lootgroup>

		<lootgroup name="FuriousRamsayGroupStarterClothes5" count="all">
			<item name="apparelTankTop" count="1"/>
			<item name="apparelDenimShortsPants" count="1"/>
			<item name="apparelRunningShoesRegular" count="1"/>
		</lootgroup>

		<lootgroup name="FuriousRamsayGroupStarterClothes6" count="all">
			<item name="apparelFlannelShirt" count="1"/>
			<item name="apparelDenimPants" count="1"/>
		</lootgroup>

		<lootgroup name="FuriousRamsayGroupStarterClothes7" count="all">
			<item name="apparelTShirtPlain" count="1"/>
			<item name="apparelGothPants" count="1"/>
			<item name="apparelRunningShoesRegular" count="1"/>
		</lootgroup>

		<lootgroup name="FuriousRamsayGroupStarterClothes8" count="all">
			<item name="apparelSuitJacket" count="1"/>
			<item name="apparelSuitPants" count="1"/>
			<item name="apparelSuitDressShoes" count="1"/>
		</lootgroup>

		<lootcontainer id="818" size="3,2" sound_open="UseActions/open_corpse" sound_close="UseActions/close_corpse" open_time="1" destroy_on_close="false">
			<item group="FuriousRamsayGroupStarterClothes2" />
		</lootcontainer>

		<lootcontainer id="819" size="3,2" sound_open="UseActions/open_corpse" sound_close="UseActions/close_corpse" open_time="1" destroy_on_close="false">
			<item group="FuriousRamsayGroupStarterClothes3" />
		</lootcontainer>

		<lootcontainer id="820" size="3,2" sound_open="UseActions/open_corpse" sound_close="UseActions/close_corpse" open_time="1" destroy_on_close="false">
			<item group="FuriousRamsayGroupStarterClothes7" />
		</lootcontainer>

		<lootcontainer id="821" size="3,2" sound_open="UseActions/open_corpse" sound_close="UseActions/close_corpse" open_time="1" destroy_on_close="false">
			<item group="FuriousRamsayGroupStarterClothes6" />
		</lootcontainer>

		<lootcontainer id="822" size="3,2" sound_open="UseActions/open_corpse" sound_close="UseActions/close_corpse" open_time="1" destroy_on_close="false">
			<item group="FuriousRamsayGroupStarterClothes5" />
		</lootcontainer>

		<lootcontainer id="823" size="3,2" sound_open="UseActions/open_corpse" sound_close="UseActions/close_corpse" open_time="1" destroy_on_close="false">
			<item group="FuriousRamsayGroupStarterClothes1" />
		</lootcontainer>

		<lootcontainer id="824" size="3,2" sound_open="UseActions/open_corpse" sound_close="UseActions/close_corpse" open_time="1" destroy_on_close="false">
			<item group="FuriousRamsayGroupStarterClothes4" />
		</lootcontainer>

		<lootcontainer id="825" size="3,2" sound_open="UseActions/open_corpse" sound_close="UseActions/close_corpse" open_time="1" destroy_on_close="false">
			<item group="FuriousRamsayGroupStarterClothes8" />
		</lootcontainer>

	</append>
    
</Config>